{
  "language": "da",
  "description": "Danish train-derived MFR dictionary for MultiLexNorm-style lexical normalization. Use high_confidence_pairs for automatic replacement; send review/ambiguous/context-sensitive pairs to target-token prompt/model fallback.",
  "source": "train-00000-of-00001.parquet",
  "train_stats": {
    "sentences": 719,
    "tokens": 16448,
    "changed_tokens": 1521,
    "changed_ratio": 0.092473,
    "distinct_changed_raw": 869
  },
  "validation_stats": {
    "sentences": 0,
    "tokens": 0,
    "changed_tokens": 0,
    "changed_ratio": 0.0
  },
  "internal_split_note": "Official validation split contains no Danish rows; MFR diagnostics use a deterministic 90/10 split of the train rows with seed=42.",
  "internal_train_stats": {
    "sentences": 647,
    "tokens": 14693,
    "changed_tokens": 1375,
    "changed_ratio": 0.093582
  },
  "internal_dev_stats": {
    "sentences": 72,
    "tokens": 1755,
    "changed_tokens": 146,
    "changed_ratio": 0.083191
  },
  "pattern_counts_train_changed_tokens": {
    "other_substitution": 561,
    "danish_letter_restore": 354,
    "accent_or_diacritic_restore": 284,
    "case_change": 169,
    "expansion_or_abbreviation_restore": 61,
    "whitespace_change": 46,
    "repeated_char_reduction": 19,
    "punctuation_or_symbol_change": 19,
    "digit_related_change": 4,
    "shortening_or_deletion": 4
  },
  "thresholds": {
    "high_confidence_pairs": "top_count>=2, top_norm_confidence>=0.85, top_norm/raw_total>=0.45, protected tokens excluded, context-sensitive short forms excluded unless manually allowed based on stability",
    "balanced_pairs_for_analysis": "high-confidence plus count>=1, top_norm_confidence>=0.75, top_norm/raw_total>=0.25; analysis/ablation only"
  },
  "high_confidence_pairs": {
    "Collagen": "Kollagen",
    "HANS": "hans",
    "Hva": "Hvad",
    "IKKE": "ikke",
    "Indefra": "indefra",
    "Jeq": "Jeg",
    "Mænd": "mænd",
    "Nogle": "nogle",
    "Ogsa": "Også",
    "Valget": "valget",
    "aegte": "ægte",
    "aeldre": "ældre",
    "aerlig": "ærlig",
    "altsa": "altså",
    "ar": "år",
    "arets": "årets",
    "arig": "årig",
    "arige": "årige",
    "ars": "års",
    "baerer": "bærer",
    "bby": "baby",
    "bli": "blive",
    "blir": "bliver",
    "brn": "børn",
    "chokolade-bar": "chokoladebar",
    "dd": "død",
    "dde": "døde",
    "desvaerre": "desværre",
    "diq": "dig",
    "ehk": "ikke",
    "ejj": "ej",
    "ek": "ikke",
    "el.": "eller",
    "englaenderne": "englænderne",
    "er-musik": "er musik",
    "f": "få",
    "faa": "få",
    "faergen": "færgen",
    "faet": "fået",
    "fet": "fået",
    "flelser": "følelser",
    "fler": "føler",
    "flger": "følger",
    "foraeldre": "forældre",
    "forldre": "forældre",
    "forsta": "forstå",
    "forstr": "forstår",
    "fortsaetter": "fortsætter",
    "fraek": "fræk",
    "fuldstndig": "fuldstændig",
    "fx": "f.eks.",
    "gar": "går",
    "glaede": "glæde",
    "glaeder": "glæder",
    "graede": "græde",
    "grd": "græd",
    "grnsen": "grænsen",
    "ha": "have",
    "haevn": "hævn",
    "haevne": "hævne",
    "hardt": "hårdt",
    "hjaelp": "hjælp",
    "hjaelpe": "hjælpe",
    "hnd": "hånd",
    "hva": "hvad",
    "hvornar": "hvornår",
    "hvornr": "hvornår",
    "idag": "i dag",
    "igang": "i gang",
    "ihvertfald": "i hvert fald",
    "iik": "ikke",
    "ik": "ikke",
    "ikk": "ikke",
    "jalouxi": "jalousi",
    "jeq": "jeg",
    "ka": "kan",
    "kaereste": "kæreste",
    "kaerste": "kæreste",
    "kommentare": "kommentarer",
    "kraefter": "kræfter",
    "kreste": "kæreste",
    "krft": "kræft",
    "krligheden": "kærligheden",
    "krver": "kræver",
    "laeberne": "læberne",
    "laegger": "lægger",
    "laekker": "lækker",
    "laenge": "længe",
    "laengere": "længere",
    "laere": "lære",
    "laerende": "lærerne",
    "laes": "læs",
    "laesning": "læsning",
    "lnge": "længe",
    "lngere": "længere",
    "made": "måde",
    "mal": "mål",
    "malmand": "målmand",
    "maneder": "måneder",
    "manqe": "mange",
    "mde": "måde",
    "miin": "min",
    "minpige": "min pige",
    "miq": "mig",
    "naeste": "næste",
    "naesten": "næsten",
    "noqet": "noget",
    "nrmest": "nærmest",
    "nsten": "næsten",
    "ogs": "også",
    "ogsa": "også",
    "oq": "og",
    "paa": "på",
    "paedofile": "pædofile",
    "paen": "pæn",
    "prvet": "prøvet",
    "rabe": "råbe",
    "rabte": "råbte",
    "rrende": "rørende",
    "sadan": "sådan",
    "saeson": "sæson",
    "saetter": "sætter",
    "savel": "såvel",
    "sd": "sød",
    "sir": "siger",
    "sjaelland": "Sjælland",
    "sla": "slå",
    "slar": "slår",
    "spaendende": "spændende",
    "sta": "stå",
    "star": "står",
    "strste": "største",
    "stte": "sætte",
    "svaerere": "sværere",
    "svaert": "svært",
    "søren": "Søren",
    "taenker": "tænker",
    "taettere": "tættere",
    "teh": "the",
    "thomsen": "Thomsen",
    "tidsgraensen": "tidsgrænsen",
    "tnker": "tænker",
    "vaek": "væk",
    "vaelg": "vælg",
    "vaerd": "værd",
    "vaere": "være",
    "vaeret": "været",
    "vaerre": "værre",
    "vaertfald": "værtfald",
    "virkeliq": "virkelig",
    "vre": "være",
    "vret": "været"
  },
  "balanced_pairs_for_analysis": {
    "AFLYST": "aflyst",
    "ANTIFA": "antifa",
    "Alle": "alle",
    "Altsa": "Altså",
    "Arbejdersmiljø": "arbejdersmiljø",
    "Aspekt": "aspekt",
    "BITTE": "bitte",
    "BLÅGÅRDSPLADS": "Blågårdsplads",
    "Baggarden": "Baggården",
    "Bloog": "blog",
    "Bruqe": "Bruge",
    "Collagen": "Kollagen",
    "D": "Det",
    "DEN": "den",
    "Diger": "Siger",
    "DiiN": "Din",
    "DrK": "DRK",
    "Dumme": "dumme",
    "ER": "er",
    "Een": "en",
    "Ejj": "Ej",
    "Ekstrem": "ekstrem",
    "FANTASTISK": "fantastisk",
    "FATTER": "fatter",
    "FEM": "fem",
    "Facebook-ven": "Facebook ven",
    "Fisk": "fisk",
    "Forfaerdeliqt": "Forfaerdeligt",
    "Forhadt": "forhadt",
    "Forldre": "Forældre",
    "Formændene": "formændene",
    "Fx": "F.eks.",
    "GENSIDIGT": "gensidigt",
    "Genudsendelser": "genudsendelser",
    "Glæd": "glæd",
    "Gutter'n": "gutterne",
    "HANS": "hans",
    "HELE": "hele",
    "HOLLA": "holla",
    "Haevnen": "Hævnen",
    "Handbold'traener": "håndboldtræner",
    "Hber": "Håber",
    "HoUse": "house",
    "Hva": "Hvad",
    "Hvert": "hvert",
    "Hvorn": "Hvornår",
    "IGEN": "igen",
    "IKK": "Ikke",
    "IKKE": "ikke",
    "INGEN": "ingen",
    "Idag": "I dag",
    "Ik": "Ikke",
    "Indefra": "indefra",
    "Ingentings": "ingentings",
    "JEG": "Jeg",
    "JO": "jo",
    "Jalouxi": "Jalousi",
    "Jeq": "Jeg",
    "Jubiiiiii": "Jubi",
    "KAOS": "kaos",
    "KUN": "kun",
    "Ka": "Kan",
    "Kaat": "kat",
    "Kont.": "Kontanthjælpsmodtagere",
    "Kre": "Kære",
    "KÆRLIGHED": "Kærlighed",
    "Laekker": "lækker",
    "Laenge": "Længe",
    "Laer": "Lær",
    "Lærerforeninger": "lærerforeninger",
    "Løkkes": "Løkke",
    "MEN": "men",
    "MERE": "mere",
    "MINE": "mine",
    "Maerkeligt": "Mærkeligt",
    "Maerker": "Mærker",
    "Mande": "mand",
    "Markante": "markante",
    "Micheal": "Michael",
    "Mine": "mine",
    "Mske": "Måske",
    "Mænd": "mænd",
    "NU": "nu",
    "Nar": "Når",
    "Nogle": "nogle",
    "Nogne": "Nogen",
    "Nr": "Når",
    "Nøøøj": "Nøj",
    "OPTR": "optræden",
    "OVERRASKELSE": "overraskelse",
    "Ogsa": "Også",
    "P": "På",
    "PLZ": "Please",
    "Pa": "På",
    "PÅ": "på",
    "RIGTIG": "rigtig",
    "RYGTET": "rygtet",
    "S": "Så",
    "SKAL": "skal",
    "SKAT": "skat",
    "SPRED": "Spred",
    "SPØRG": "spørg",
    "Sa": "Så",
    "SaH": "så",
    "Saadan": "sådan",
    "Sadan": "Sådan",
    "Satire": "satire",
    "Schaumburg-muller": "Schaumburg-Muller",
    "Soger": "Siger",
    "Specieelt": "specielt",
    "StarFucker": "starfucker",
    "Svedkon": "sved",
    "Syngdom": "Sygdom",
    "SÅÅÅÅ": "så",
    "SØGER": "Søger",
    "SØNDAG": "søndag",
    "Sååå": "Så",
    "Såååå": "Så",
    "TAK": "tak",
    "TIDEN": "tiden",
    "TJEK": "tjek",
    "Taenk": "Tænk",
    "Thai": "thai",
    "Tjaaa": "tja",
    "Turmalet": "tour målet",
    "Tømmermaend": "Tømmermænd",
    "Valget": "valget",
    "Via": "via",
    "YAY": "Yay",
    "_Hej": "Hej",
    "_Ingen": "Ingen",
    "_jeg": "jeg",
    "_skal_": "skal",
    "a": "at",
    "abenbart": "åbenbart",
    "abenlyst": "åbenlyst",
    "abne": "åbne",
    "adolf": "Adolf",
    "aede": "æde",
    "aedofili": "pædofili",
    "aegte": "ægte",
    "aeldre": "ældre",
    "aengstelig": "ængstelig",
    "aer": "ær",
    "aeren": "æren",
    "aerlig": "ærlig",
    "aermet": "ærmet",
    "aes": "æs",
    "aevn": "ævn",
    "afhngig": "afhængig",
    "aktespterre": "aktespterer",
    "aldriq": "aldrig",
    "alrdig": "aldrig",
    "alts": "altså",
    "altsa": "altså",
    "amalie": "Amalie",
    "amela": "Amela",
    "anne-sofie": "Anne-Sofie",
    "ansøqt": "ansøgt",
    "ar": "år",
    "arb.markedet": "arbejsmarkedet",
    "arene": "årene",
    "arets": "årets",
    "arig": "årig",
    "arige": "årige",
    "ars": "års",
    "autoqraf": "autograf",
    "awsomeste": "awesomeste",
    "bade": "både",
    "badevaerelset": "badeværelset",
    "baer": "bær",
    "baerer": "bærer",
    "baeres": "bæres",
    "bang": "Bang",
    "bby": "baby",
    "bedeen": "bede en",
    "bedsteforldre": "bedsteforældre",
    "behyndte": "begyndte",
    "bekraeftet": "bekræftet",
    "bemaerket": "bemærket",
    "besaettelse": "besættelse",
    "besvaeret": "besværet",
    "besvaerlig": "besværlig",
    "billedkvali": "billedkvalitet",
    "bla": "blå",
    "bli": "blive",
    "blir": "bliver",
    "blkregning": "blækregning",
    "blokere": "Bloker",
    "bne": "åbne",
    "bner": "åbner",
    "braek": "bræk",
    "braekkede": "brækkede",
    "braekker": "brækker",
    "braemsespor": "bremsespor",
    "braendalarmen": "brandalarmen",
    "brn": "børn",
    "brnepasning": "børnepasning",
    "bruqe": "bruge",
    "bush": "Bush",
    "chillarn": "chilleren",
    "chokolade-bar": "chokoladebar",
    "collagen": "kollagen",
    "coquelin": "Coquelin",
    "dR": "der",
    "daekket": "dækket",
    "dagobog": "dagbog",
    "darlig": "dårlig",
    "darligt": "dårligt",
    "dd": "død",
    "dde": "døde",
    "dden": "døden",
    "deee": "det",
    "deejliige": "dejliige",
    "destromindre": "desto mindre",
    "desv": "desværre",
    "desvaerer": "desværre",
    "desvaerre": "desværre",
    "desvrre": "desværre",
    "dgn": "døgn",
    "diig": "dig",
    "diin": "din",
    "dilmurat": "Dilmurat",
    "dilraba": "Dilraba",
    "diq": "dig",
    "diskoterede": "diskuterede",
    "dk": "DK",
    "draeber": "dræber",
    "dreams": "Dreams",
    "dren": "døren",
    "dvaerg": "dværg",
    "dvs": "dvs.",
    "dybt": "Dybt",
    "där": "hvor",
    "dårligt": "dårlig",
    "eej": "ej",
    "efterskole": "Efterskole",
    "ehk": "ikke",
    "ejj": "ej",
    "ek": "ikke",
    "el.": "eller",
    "el.lign": "eller lignende",
    "endu": "endnu",
    "engholm": "Engholm",
    "englaenderne": "englænderne",
    "enmandshaeren": "enmandshæren",
    "er-musik": "er musik",
    "etpartiregring": "etpartiregering",
    "europa": "Europa",
    "eviiiigt": "evigt",
    "ex-kaereste": "ekskæreste",
    "f": "få",
    "faa": "få",
    "faar": "får",
    "fael": "fæl",
    "faenomenale": "fænomenale",
    "faerdig": "færdig",
    "faergen": "færgen",
    "faet": "fået",
    "faetter": "fætter",
    "faldte": "faldt",
    "familie-medlemmer": "familiemedlemmer",
    "famillie": "familie",
    "fanme": "fandme",
    "fb": "Facebook",
    "fdselsdagssange": "fødselsdagssange",
    "fet": "fået",
    "filmven": "film ven",
    "fle": "føle",
    "flelse": "følelse",
    "flelsen": "følelsen",
    "flelser": "følelser",
    "fler": "føler",
    "fles": "føles",
    "flesteet": "fleste",
    "flge": "følge",
    "flger": "følger",
    "fodi": "fordi",
    "fof": "for",
    "foraeldre": "forældre",
    "foraeldrenes": "forældrenes",
    "forelskelse": "forelskede",
    "forfaerdeligt": "forfærdeligt",
    "forfrdeligt": "forfærdeligt",
    "forkaelet": "forkælet",
    "forldre": "forældre",
    "forldrene": "forældrene",
    "forlovses": "forlovelses",
    "forsaetter": "forsætter",
    "forskelliqe": "forskellige",
    "forsorgshjem": "Forsorgshjem",
    "forsta": "forstå",
    "forstaet": "forstået",
    "forstar": "forstår",
    "forstr": "forstår",
    "fortaelle": "fortælle",
    "fortaeller": "fortæller",
    "fortiden": "for tiden",
    "fortller": "fortæller",
    "fortraenge": "fortrænge",
    "fortsaetter": "fortsætter",
    "forældre-generation": "forældregeneration",
    "fraek": "fræk",
    "franskmaend": "franskmænd",
    "frdig": "færdig",
    "frdige": "færdige",
    "fremgar": "fremgår",
    "frida": "Frida",
    "frst": "først",
    "frste": "første",
    "frygt-gruppe": "frygt gruppe",
    "fuldmane": "fuldmåne",
    "fuldmanen": "fuldmånen",
    "fuldstaendigt": "fuldstændigt",
    "fuldstndig": "fuldstændig",
    "fx": "f.eks.",
    "føre": "fører",
    "gaest": "gæst",
    "gaestebogen": "gæstebogen",
    "gaet": "gået",
    "gar": "går",
    "garsdagens": "gårsdagens",
    "gaturer": "gåture",
    "gennemgaet": "gennemgået",
    "gennemgs": "gennemgås",
    "get": "godt",
    "ginial": "genial",
    "girne": "grine",
    "gjordt": "gjort",
    "glaede": "glæde",
    "glaeden": "glæden",
    "glaeder": "glæder",
    "glimmet": "glimtet",
    "go": "god",
    "goergh": "George",
    "graede": "græde",
    "graeder": "græder",
    "grd": "græd",
    "grde": "græde",
    "grder": "græder",
    "gre": "gør",
    "grell": "Grell",
    "grnsen": "grænsen",
    "guldborgsund": "Guldborgsund",
    "ha": "have",
    "haai": "hej",
    "haaj": "hej",
    "haar": "har",
    "hab": "håb",
    "habefulde": "håbefulde",
    "haber": "håber",
    "haenderne": "hænderne",
    "haeren": "hæren",
    "haevn": "hævn",
    "haevne": "hævne",
    "haevnlyst": "hævnlyst",
    "haevnlysten": "hævnlysten",
    "hakimi": "Hakimi",
    "hamre": "hamrer",
    "hand": "hånd",
    "handtaget": "håndtaget",
    "happiness": "Happiness",
    "hardag": "hårdag",
    "hardt": "hårdt",
    "hasseb": "Hasseb",
    "hber": "håber",
    "helsingør": "Helsingør",
    "hende": "hendes",
    "hitler": "Hitler",
    "hjaelp": "hjælp",
    "hjaelpe": "hjælpe",
    "hjaelpende": "hjælpende",
    "hjaelper": "hjælper",
    "hjlper": "hjælper",
    "hjælpmodtagere": "",
    "hnd": "hånd",
    "honore": "Honore",
    "hoved": "hovedet",
    "hovede": "hoved",
    "hovedt": "hovedet",
    "hrer": "høre",
    "hvA": "hvad",
    "hva": "hvad",
    "hvertfald": "hvert fald",
    "hvornar": "hvornår",
    "hvornr": "hvornår",
    "hvorpa": "hvorpå",
    "høre": "hører",
    "hører": "høre",
    "iN": "in",
    "iS": "is",
    "ida": "Ida",
    "idag": "i dag",
    "iden": "idéen",
    "ift": "ift.",
    "ig": "og",
    "igang": "i gang",
    "igr": "i går",
    "igår": "i går",
    "ihvertfald": "i hvert fald",
    "ii": "i",
    "iik": "ikke",
    "ik": "ikke",
    "ikk": "ikke",
    "imorgen": "i morgen",
    "indanding": "indånding",
    "indebaere": "indebære",
    "indlaeg": "indlag",
    "indrmme": "indrømme",
    "indtrder": "indtærder",
    "interes": "interesse",
    "intw": "interview",
    "iqen": "igen",
    "iqennem": "igennem",
    "isabell": "Isabell",
    "isr": "især",
    "isteden": "i stedet",
    "istedet": "i stedet",
    "ivejen": "i vejen",
    "iøvrigt": "i øvrigt",
    "jae": "ja",
    "jaevnligt": "jævnligt",
    "jalouxi": "jalousi",
    "jean": "Jean",
    "jehovah": "Jehovah",
    "jekast": "øjekast",
    "jensen": "Jensen",
    "jeq": "jeg",
    "jne": "øjne",
    "jubilaeum": "jubilæum",
    "ka": "kan",
    "kaeft": "kæft",
    "kaelderen": "kælderen",
    "kaemper": "kæmper",
    "kaereste": "kæreste",
    "kaeresten": "kæresten",
    "kaerester": "kærester",
    "kaerlighed": "kærlighed",
    "kaerste": "kæreste",
    "kanon-konge": "kanon konge",
    "karet": "kåret",
    "kedte": "kendte",
    "kierlighed": "kærlighed",
    "kjøwenhavneri": "københavneri",
    "klaer": "klæder",
    "knae": "knaæ",
    "knaebbe": "kneppe",
    "knaebber": "knepper",
    "knaegt": "knægt",
    "koldingstorcenter": "Kolding Storcenter",
    "kollegar": "kollegaer",
    "kolleger": "kollegaer",
    "kommentare": "kommentarer",
    "kommentator-uge": "kommentator uge",
    "kommunes": "Kommunes",
    "konomisk": "økonomisk",
    "konomiske": "økonomiske",
    "kontrolle": "kontrollere",
    "koraner": "Koraner",
    "kraefter": "kræfter",
    "kraever": "kræver",
    "kreste": "kæreste",
    "krester": "kærester",
    "krft": "kræft",
    "krften": "kræften",
    "krfter": "kræfter",
    "krligheden": "kærligheden",
    "krver": "kræver",
    "krves": "kræves",
    "ku": "kunne",
    "kvaern": "kværn",
    "kærlighed'-par": "kærlighed par",
    "købene": "købende",
    "kølskabs-smørbart": "kølskabssmørbart",
    "la": "lå",
    "laaaaaaang": "lang",
    "laaaang": "lang",
    "lae": "læ",
    "laeber": "læber",
    "laeberne": "læberne",
    "laegen": "lægen",
    "laegerne": "lægerne",
    "laegge": "lægge",
    "laegger": "lægger",
    "laekker": "lækker",
    "laenge": "længe",
    "laengere": "længere",
    "laengst": "længst",
    "laere": "lære",
    "laerende": "lærerne",
    "laerer": "lærer",
    "laes": "læs",
    "laese": "læse",
    "laeser": "læser",
    "laesere": "læsere",
    "laesning": "læsning",
    "laest": "læst",
    "landsholdsmal": "landsholdsmål",
    "ld": "lød",
    "ldes": "ældes",
    "lego": "Lego",
    "ligefr": "ligefør",
    "ligegald-området": "ligegald området",
    "ligeså": "lige så",
    "lilleby": "lille by",
    "linette": "Linette",
    "liqe": "lige",
    "livsglde": "livsglæde",
    "llen": "øllen",
    "lnge": "længe",
    "lngere": "længere",
    "lngst": "længst",
    "looove": "love",
    "louise": "Louise",
    "lre": "lære",
    "lse": "læse",
    "lser": "læser",
    "lsning": "løsning",
    "lst": "løst",
    "luk": "lukke",
    "m": "må",
    "ma": "må",
    "maaN": "mand",
    "maaaaaan": "mand",
    "maaain": "mand",
    "maaayn": "mand",
    "made": "måde",
    "mader": "måder",
    "maegtig": "mægtig",
    "maegtige": "mægtige",
    "maend": "mænd",
    "maerke": "mærke",
    "maerkedage": "mærkedage",
    "maerkede": "mærkede",
    "maerkeliqe": "mærkeligt",
    "mal": "mål",
    "malhelt": "målhelt",
    "malmand": "målmand",
    "malscorer": "målscore",
    "maltavlen": "måltavlen",
    "maltyv": "måltyv",
    "manedens": "månedens",
    "maneder": "måneder",
    "mann": "man",
    "manqe": "mange",
    "maria": "Maria",
    "matilde": "Matilde",
    "matte": "måtte",
    "mattson": "Mattson",
    "mattsson": "Mattsson",
    "mde": "måde",
    "mdl": "månedligt",
    "meddelser": "meddelelser",
    "meeget": "meget",
    "mega'Glad": "mega glad",
    "mega-sjov": "mega sjov",
    "menning": "mening",
    "mer": "mere",
    "mercedes": "Mercedes",
    "mette": "Mette",
    "midtjylland": "Midtjylland",
    "miig": "mig",
    "miin": "min",
    "miiq": "mig",
    "miit": "mit",
    "mikkelsen": "Mikkelsen",
    "minpige": "min pige",
    "minut.Vi": "minut. Vi",
    "miq": "mig",
    "misforstaet": "misforstået",
    "mivs": "Mivs",
    "modes": "modnes",
    "modsaetning": "modsætning",
    "modstninger": "modsætninger",
    "mrke": "mørke",
    "mrkede": "mærkede",
    "mske": "måske",
    "muliqe": "mulige",
    "munder": "munden",
    "muuuuligt": "muligt",
    "måder": "måde",
    "mån": "måneder",
    "na": "når",
    "naeae": "næ",
    "naegter": "nægter",
    "naej": "nej",
    "naesen": "næsen",
    "naeste": "næste",
    "naesten": "næsten",
    "naestved": "Næstved",
    "naet": "nået",
    "nar": "når",
    "nattebesøge": "nattebesøg",
    "niiice": "nice",
    "noqenlunde": "nogenlunde",
    "noqet": "noget",
    "nr": "når",
    "nrmest": "nærmest",
    "nsten": "næsten",
    "ntterne": "nætterne",
    "nuet": "nu'et",
    "nullermaend": "nullermænd",
    "nuvaerende": "nuværende",
    "ny": "nu",
    "odense": "Odense",
    "ogs": "også",
    "ogsa": "også",
    "okah": "okay",
    "okey": "okay",
    "omrader": "områder",
    "ondsvagt": "åndsvagt",
    "opfattelse": "opfattelser",
    "opmaerksomhed": "opmærksomhed",
    "opsaetning": "opsætning",
    "opsta": "opstå",
    "optraede": "optræde",
    "oq": "og",
    "oqs": "også",
    "osse": "også",
    "overhovdet": "overhovedet",
    "overstte": "oversætte",
    "p": "på",
    "pa": "på",
    "paa": "på",
    "paedofile": "pædofile",
    "paedofiles": "pædofiles",
    "paedofili": "pædofili",
    "paen": "pæn",
    "paenere": "pænere",
    "pagaeldende": "pågældende",
    "paramore": "Paramore",
    "paul": "Paul",
    "pavirket": "påvirket",
    "penqe": "penge",
    "petersen": "Petersen",
    "pga": "pga.",
    "piqe": "pige",
    "pokal-bold": "pokal bold",
    "pokal-charme": "pokal charme",
    "poltiker-snak": "poltiker snak",
    "prcis": "præcis",
    "prv": "prøv",
    "prve": "prøve",
    "prvet": "prøvet",
    "psykobilled": "psykobillede",
    "qanqe": "gange",
    "qerne": "gerne",
    "qive": "give",
    "qr": "qør",
    "rabe": "råbe",
    "rabte": "råbte",
    "reddit": "Reddit",
    "repraesentanter": "repræsentanter",
    "retter": "rettere",
    "rigtigk": "rigtig",
    "rinqet": "ringet",
    "rkker": "rækker",
    "rliqt": "ærligt",
    "rrende": "rørende",
    "rver-historier": "røver-historier",
    "rådt": "råt",
    "røqet": "røget",
    "s": "så",
    "sa": "så",
    "saa": "så",
    "saaaa": "så",
    "sadan": "sådan",
    "sae": "så",
    "saelger": "sælger",
    "saeriøst": "særiøst",
    "saerklasse": "særklasse",
    "saerlig": "særlig",
    "saeson": "sæson",
    "saesonen": "sæsonen",
    "saetning": "sætning",
    "saetter": "sætter",
    "sakaldte": "såkaldte",
    "samn": "sammen",
    "sandgaard": "Sandgaard",
    "sarah": "Sarah",
    "sarn": "sådan",
    "savel": "såvel",
    "saxenhøj": "Saxenhøj",
    "sd": "sød",
    "sdan": "sådan",
    "sdt": "sødt",
    "seej": "sej",
    "sejer": "sejere",
    "selvtaegt": "selvtægt",
    "selvvaerd": "selvværd",
    "sen": "sådan",
    "senarie": "scenarie",
    "serie-hold": "seriehold",
    "sg": "sgu",
    "shirt": "shit",
    "simone": "Simone",
    "sir": "siger",
    "sjaelden": "sjælden",
    "sjaelland": "Sjælland",
    "sk": "skær",
    "skaath": "skat",
    "skabren": "skaberen",
    "skbnesvanger": "skæbnesvanger",
    "sknt": "skønt",
    "skraemmende": "skræmmende",
    "skrmen": "skærmen",
    "sla": "slå",
    "slaet": "slået",
    "slar": "slår",
    "slfejl": "slåfejl",
    "sluk": "slukke",
    "sma's": "små's",
    "spaendende": "spændende",
    "spaerrer": "spærrer",
    "spilelr": "spiller",
    "spraeller": "spræller",
    "sprgsmlet": "spørgsmålet",
    "sprgsmlstegn": "spørgsmålstegn",
    "sq": "sgu",
    "squ": "sgu",
    "srdeleshed": "særdeleshed",
    "sret": "såret",
    "srlig": "særlig",
    "sster": "søster",
    "sta": "stå",
    "staerk": "stærk",
    "staerkt": "stærkt",
    "star": "står",
    "staret": "startet",
    "stinne": "Stinne",
    "stjaeler": "stjæler",
    "str": "står",
    "strkt": "stærkt",
    "strste": "største",
    "strøget": "Strøget",
    "stte": "sætte",
    "sttte": "støtte",
    "svaekket": "svækket",
    "svaerere": "sværere",
    "svaert": "svært",
    "svart": "svært",
    "svel": "selv",
    "svn": "søvn",
    "svr": "svær",
    "svrt": "svært",
    "sygete": "sygeste",
    "syndes": "synes",
    "syntes": "synes",
    "sys": "synes",
    "sølvørering": "sølv ørering",
    "søren": "Søren",
    "taeller": "tæller",
    "taender": "tænder",
    "taenk": "tænk",
    "taenker": "tænker",
    "taenkt": "tænkt",
    "taettere": "tættere",
    "tankelaesere": "tankelæsere",
    "tare": "tårer",
    "teenage": "teenager",
    "teh": "the",
    "the": "The",
    "thomsen": "Thomsen",
    "tidsgraensen": "tidsgrænsen",
    "tilfaeldigt": "tilfældigt",
    "tilfje": "tilføje",
    "tilstrkkeligt": "tilstrækkeligt",
    "tiltraekke": "tiltrække",
    "tittle": "title",
    "tnke": "tænke",
    "tnker": "tænker",
    "toiletbraedtet": "toiletbrættet",
    "traejen": "trøjen",
    "traek": "træk",
    "traekke": "trække",
    "traels": "træls",
    "traette": "trætte",
    "tre": "tårer",
    "trer": "tårer",
    "trt": "træt",
    "tt": "tæt",
    "uff": "uf",
    "ulaekkert": "ulækkert",
    "umaid": "Umaid",
    "undskyld": "Undskyld",
    "vad": "våd",
    "vaek": "væk",
    "vaelg": "vælg",
    "vaerd": "værd",
    "vaerdifulde": "værdifulde",
    "vaere": "være",
    "vaerelse": "værelse",
    "vaerer": "være",
    "vaerere": "værre",
    "vaeret": "været",
    "vaerre": "værre",
    "vaerste": "værste",
    "vaertfald": "værtfald",
    "vaesentligt": "væsentligt",
    "vars": "var",
    "vernden": "verden",
    "vilken": "hvilken",
    "virkeliiq": "virkelig",
    "virkeliq": "virkelig",
    "vre": "være",
    "vrelset": "værelset",
    "vret": "været",
    "vrket": "værket",
    "vrste": "værste",
    "wooow": "wow",
    "x-factor": "X-Factor",
    "xtra": "ekstra",
    "Årskonference": "årskonference",
    "ÆDEN": "",
    "Ælsker": "Elsker",
    "Én": "én",
    "ææælsker": "elsker",
    "ødelaegge": "ødelægge",
    "ødelaeggelse": "ødelæggelse",
    "ødelaeggende": "ødelæggende",
    "østeuropæere": "Østeuropæere"
  },
  "review_pairs": {
    "3.verdenskrig": {
      "top_norm": "3. verdenskrig",
      "top_count": 1,
      "raw_total": 1,
      "changed_total": 1,
      "changed_confidence": 1.0,
      "raw_confidence": 1.0,
      "candidates": {
        "3. verdenskrig": 1
      }
    },
    "Da": {
      "top_norm": "the",
      "top_count": 1,
      "raw_total": 5,
      "changed_total": 1,
      "changed_confidence": 1.0,
      "raw_confidence": 0.2,
      "candidates": {
        "the": 1
      }
    },
    "Min": {
      "top_norm": "min",
      "top_count": 1,
      "raw_total": 9,
      "changed_total": 1,
      "changed_confidence": 1.0,
      "raw_confidence": 0.1111,
      "candidates": {
        "min": 1
      }
    },
    "har": {
      "top_norm": "hår",
      "top_count": 5,
      "raw_total": 183,
      "changed_total": 5,
      "changed_confidence": 1.0,
      "raw_confidence": 0.0273,
      "candidates": {
        "hår": 5
      }
    },
    "du": {
      "top_norm": "Du",
      "top_count": 1,
      "raw_total": 108,
      "changed_total": 1,
      "changed_confidence": 1.0,
      "raw_confidence": 0.0093,
      "candidates": {
        "Du": 1
      }
    },
    "det": {
      "top_norm": "der",
      "top_count": 1,
      "raw_total": 285,
      "changed_total": 1,
      "changed_confidence": 1.0,
      "raw_confidence": 0.0035,
      "candidates": {
        "der": 1
      }
    },
    "gøre": {
      "top_norm": "gør",
      "top_count": 2,
      "raw_total": 11,
      "changed_total": 2,
      "changed_confidence": 1.0,
      "raw_confidence": 0.1818,
      "candidates": {
        "gør": 2
      }
    },
    "HV0RF0R": {
      "top_norm": "hvorfor",
      "top_count": 1,
      "raw_total": 1,
      "changed_total": 1,
      "changed_confidence": 1.0,
      "raw_confidence": 1.0,
      "candidates": {
        "hvorfor": 1
      }
    },
    "man": {
      "top_norm": "mand",
      "top_count": 2,
      "raw_total": 58,
      "changed_total": 2,
      "changed_confidence": 1.0,
      "raw_confidence": 0.0345,
      "candidates": {
        "mand": 2
      }
    },
    "far": {
      "top_norm": "for",
      "top_count": 1,
      "raw_total": 8,
      "changed_total": 1,
      "changed_confidence": 1.0,
      "raw_confidence": 0.125,
      "candidates": {
        "for": 1
      }
    },
    "nogen": {
      "top_norm": "nogle",
      "top_count": 1,
      "raw_total": 14,
      "changed_total": 1,
      "changed_confidence": 1.0,
      "raw_confidence": 0.0714,
      "candidates": {
        "nogle": 1
      }
    },
    "Nej": {
      "top_norm": "nej",
      "top_count": 1,
      "raw_total": 5,
      "changed_total": 1,
      "changed_confidence": 1.0,
      "raw_confidence": 0.2,
      "candidates": {
        "nej": 1
      }
    },
    "spørgsmal": {
      "top_norm": "spørgsmål",
      "top_count": 1,
      "raw_total": 6,
      "changed_total": 1,
      "changed_confidence": 1.0,
      "raw_confidence": 0.1667,
      "candidates": {
        "spørgsmål": 1
      }
    },
    "Jeg": {
      "top_norm": "jeg",
      "top_count": 4,
      "raw_total": 90,
      "changed_total": 4,
      "changed_confidence": 1.0,
      "raw_confidence": 0.0444,
      "candidates": {
        "jeg": 4
      }
    },
    "1.virusstreng": {
      "top_norm": "1. virusstreng",
      "top_count": 1,
      "raw_total": 1,
      "changed_total": 1,
      "changed_confidence": 1.0,
      "raw_confidence": 1.0,
      "candidates": {
        "1. virusstreng": 1
      }
    },
    "nu": {
      "top_norm": "Nu",
      "top_count": 1,
      "raw_total": 25,
      "changed_total": 1,
      "changed_confidence": 1.0,
      "raw_confidence": 0.04,
      "candidates": {
        "Nu": 1
      }
    },
    "altså": {
      "top_norm": "Altså",
      "top_count": 1,
      "raw_total": 8,
      "changed_total": 1,
      "changed_confidence": 1.0,
      "raw_confidence": 0.125,
      "candidates": {
        "Altså": 1
      }
    },
    "alle": {
      "top_norm": "Alle",
      "top_count": 1,
      "raw_total": 25,
      "changed_total": 1,
      "changed_confidence": 1.0,
      "raw_confidence": 0.04,
      "candidates": {
        "Alle": 1
      }
    },
    "dag": {
      "top_norm": "dage",
      "top_count": 1,
      "raw_total": 12,
      "changed_total": 1,
      "changed_confidence": 1.0,
      "raw_confidence": 0.0833,
      "candidates": {
        "dage": 1
      }
    },
    "racistisk": {
      "top_norm": "racistiske",
      "top_count": 2,
      "raw_total": 18,
      "changed_total": 2,
      "changed_confidence": 1.0,
      "raw_confidence": 0.1111,
      "candidates": {
        "racistiske": 2
      }
    },
    ".": {
      "top_norm": "",
      "top_count": 2,
      "raw_total": 691,
      "changed_total": 2,
      "changed_confidence": 1.0,
      "raw_confidence": 0.0029,
      "candidates": {
        "": 2
      }
    },
    "der": {
      "top_norm": "Ser",
      "top_count": 1,
      "raw_total": 126,
      "changed_total": 1,
      "changed_confidence": 1.0,
      "raw_confidence": 0.0079,
      "candidates": {
        "Ser": 1
      }
    },
    "sjov": {
      "top_norm": "sjove",
      "top_count": 2,
      "raw_total": 46,
      "changed_total": 2,
      "changed_confidence": 1.0,
      "raw_confidence": 0.0435,
      "candidates": {
        "sjove": 2
      }
    },
    "1ustoppelig": {
      "top_norm": "ustoppelig",
      "top_count": 1,
      "raw_total": 1,
      "changed_total": 1,
      "changed_confidence": 1.0,
      "raw_confidence": 1.0,
      "candidates": {
        "ustoppelig": 1
      }
    },
    "og": {
      "top_norm": "Og",
      "top_count": 1,
      "raw_total": 362,
      "changed_total": 1,
      "changed_confidence": 1.0,
      "raw_confidence": 0.0028,
      "candidates": {
        "Og": 1
      }
    },
    "I": {
      "top_norm": "i",
      "top_count": 1,
      "raw_total": 27,
      "changed_total": 1,
      "changed_confidence": 1.0,
      "raw_confidence": 0.037,
      "candidates": {
        "i": 1
      }
    },
    "dem": {
      "top_norm": "den",
      "top_count": 1,
      "raw_total": 26,
      "changed_total": 1,
      "changed_confidence": 1.0,
      "raw_confidence": 0.0385,
      "candidates": {
        "den": 1
      }
    },
    "en": {
      "top_norm": "et",
      "top_count": 1,
      "raw_total": 242,
      "changed_total": 1,
      "changed_confidence": 1.0,
      "raw_confidence": 0.0041,
      "candidates": {
        "et": 1
      }
    },
    "iq70": {
      "top_norm": "IQ70",
      "top_count": 1,
      "raw_total": 1,
      "changed_total": 1,
      "changed_confidence": 1.0,
      "raw_confidence": 1.0,
      "candidates": {
        "IQ70": 1
      }
    },
    "nogle": {
      "top_norm": "nogen",
      "top_count": 1,
      "raw_total": 14,
      "changed_total": 1,
      "changed_confidence": 1.0,
      "raw_confidence": 0.0714,
      "candidates": {
        "nogen": 1
      }
    },
    "Det": {
      "top_norm": "det",
      "top_count": 3,
      "raw_total": 77,
      "changed_total": 3,
      "changed_confidence": 1.0,
      "raw_confidence": 0.039,
      "candidates": {
        "det": 3
      }
    },
    "Dr3": {
      "top_norm": "DR3",
      "top_count": 1,
      "raw_total": 1,
      "changed_total": 1,
      "changed_confidence": 1.0,
      "raw_confidence": 1.0,
      "candidates": {
        "DR3": 1
      }
    },
    "Dr1": {
      "top_norm": "DR1",
      "top_count": 1,
      "raw_total": 1,
      "changed_total": 1,
      "changed_confidence": 1.0,
      "raw_confidence": 1.0,
      "candidates": {
        "DR1": 1
      }
    },
    "Dr2": {
      "top_norm": "DR2",
      "top_count": 1,
      "raw_total": 1,
      "changed_total": 1,
      "changed_confidence": 1.0,
      "raw_confidence": 1.0,
      "candidates": {
        "DR2": 1
      }
    },
    "En": {
      "top_norm": "en",
      "top_count": 1,
      "raw_total": 13,
      "changed_total": 1,
      "changed_confidence": 1.0,
      "raw_confidence": 0.0769,
      "candidates": {
        "en": 1
      }
    },
    "Den": {
      "top_norm": "den",
      "top_count": 1,
      "raw_total": 14,
      "changed_total": 1,
      "changed_confidence": 1.0,
      "raw_confidence": 0.0714,
      "candidates": {
        "den": 1
      }
    },
    "kommer": {
      "top_norm": "Kommer",
      "top_count": 1,
      "raw_total": 20,
      "changed_total": 1,
      "changed_confidence": 1.0,
      "raw_confidence": 0.05,
      "candidates": {
        "Kommer": 1
      }
    },
    "Og": {
      "top_norm": "og",
      "top_count": 1,
      "raw_total": 19,
      "changed_total": 1,
      "changed_confidence": 1.0,
      "raw_confidence": 0.0526,
      "candidates": {
        "og": 1
      }
    }
  },
  "ambiguous_pairs": {
    "taenke": {
      "top_norm": "tænke",
      "top_count": 4,
      "raw_total": 5,
      "changed_total": 5,
      "changed_confidence": 0.8,
      "raw_confidence": 0.8,
      "candidates": {
        "tænke": 4,
        "tænkte": 1
      }
    },
    "sku": {
      "top_norm": "sgu",
      "top_count": 9,
      "raw_total": 10,
      "changed_total": 10,
      "changed_confidence": 0.9,
      "raw_confidence": 0.9,
      "candidates": {
        "sgu": 9,
        "skulle": 1
      }
    },
    "os": {
      "top_norm": "også",
      "top_count": 2,
      "raw_total": 15,
      "changed_total": 3,
      "changed_confidence": 0.6667,
      "raw_confidence": 0.1333,
      "candidates": {
        "også": 2,
        "Os": 1
      }
    },
    "gr": {
      "top_norm": "går",
      "top_count": 5,
      "raw_total": 8,
      "changed_total": 8,
      "changed_confidence": 0.625,
      "raw_confidence": 0.625,
      "candidates": {
        "går": 5,
        "gør": 3
      }
    },
    "fa": {
      "top_norm": "få",
      "top_count": 4,
      "raw_total": 5,
      "changed_total": 5,
      "changed_confidence": 0.8,
      "raw_confidence": 0.8,
      "candidates": {
        "få": 4,
        "får": 1
      }
    },
    "bedmme": {
      "top_norm": "bestemme",
      "top_count": 1,
      "raw_total": 2,
      "changed_total": 2,
      "changed_confidence": 0.5,
      "raw_confidence": 0.5,
      "candidates": {
        "bestemme": 1,
        "bedømme": 1
      }
    },
    "r": {
      "top_norm": "er",
      "top_count": 3,
      "raw_total": 6,
      "changed_total": 6,
      "changed_confidence": 0.5,
      "raw_confidence": 0.5,
      "candidates": {
        "er": 3,
        "år": 3
      }
    },
    "fr": {
      "top_norm": "får",
      "top_count": 2,
      "raw_total": 3,
      "changed_total": 3,
      "changed_confidence": 0.6667,
      "raw_confidence": 0.6667,
      "candidates": {
        "får": 2,
        "før": 1
      }
    },
    "n": {
      "top_norm": "når",
      "top_count": 1,
      "raw_total": 2,
      "changed_total": 2,
      "changed_confidence": 0.5,
      "raw_confidence": 0.5,
      "candidates": {
        "når": 1,
        "næ": 1
      }
    },
    "t": {
      "top_norm": "",
      "top_count": 2,
      "raw_total": 5,
      "changed_total": 3,
      "changed_confidence": 0.6667,
      "raw_confidence": 0.4,
      "candidates": {
        "": 2,
        "til": 1
      }
    }
  },
  "context_sensitive_tokens": [
    "a",
    "af",
    "at",
    "d",
    "de",
    "den",
    "der",
    "det",
    "dig",
    "dk",
    "dm",
    "du",
    "eu",
    "fa",
    "fr",
    "fx",
    "få",
    "gr",
    "går",
    "gør",
    "har",
    "hva",
    "hvad",
    "hår",
    "i",
    "j",
    "jeg",
    "jeq",
    "ka",
    "kan",
    "ku",
    "kun",
    "la",
    "lol",
    "ma",
    "man",
    "mattson",
    "me",
    "med",
    "men",
    "mig",
    "min",
    "miq",
    "må",
    "n",
    "na",
    "nar",
    "nr",
    "når",
    "o",
    "og",
    "ok",
    "oq",
    "os",
    "p",
    "pa",
    "paa",
    "pc",
    "pga",
    "på",
    "r",
    "rt",
    "s",
    "sa",
    "saa",
    "sgu",
    "sku",
    "sq",
    "squ",
    "så",
    "t",
    "ta",
    "til",
    "tv",
    "usa",
    "v",
    "va",
    "var",
    "vi",
    "være"
  ],
  "paper_seed_pairs": {
    "pa": "på",
    "paa": "på",
    "p": "på",
    "sa": "så",
    "saa": "så",
    "s": "så",
    "ma": "må",
    "vaere": "være",
    "vaeret": "været",
    "vaek": "væk",
    "laekker": "lækker",
    "naesten": "næsten",
    "saeson": "sæson",
    "taenker": "tænker",
    "hjaelp": "hjælp",
    "ikk": "ikke",
    "ik": "ikke",
    "ek": "ikke",
    "ogs": "også",
    "ogsa": "også",
    "hva": "hvad",
    "ka": "kan",
    "ha": "have",
    "blir": "bliver",
    "jeq": "jeg",
    "oq": "og",
    "diq": "dig",
    "miq": "mig",
    "noqet": "noget",
    "idag": "i dag",
    "minpige": "min pige",
    "pga": "pga.",
    "fx": "f.eks."
  },
  "notes": [
    "Danish official validation rows are absent in the provided validation split; use internal-dev or cross-validation for ablation.",
    "Danish-specific letters æ/ø/å are often missing in social-media spellings, commonly represented as ae/oe/aa or plain ASCII forms.",
    "Very short tokens such as pa/p/s/sa/a/r/gr/fr/fa/n/t are context-sensitive and should often go to target-token prompt/model fallback unless high-confidence evidence supports a direct replacement.",
    "Hashtags, mentions, URLs, numbers, alphanumeric entities, and named entities remain protected."
  ]
}